memtrace/__init__.py
memtrace/__main__.py
memtrace/core.py
python_memtrace-0.0.1.dist-info/METADATA
python_memtrace-0.0.1.dist-info/WHEEL
python_memtrace-0.0.1.dist-info/top_level.txt
python_memtrace-0.0.1.dist-info/RECORD
